setup.py
distributions/Binomialdistribution.py
distributions/Gaussiandistribution.py
distributions/Generaldistribution.py
distributions/__init__.py
prop_test.egg-info/PKG-INFO
prop_test.egg-info/SOURCES.txt
prop_test.egg-info/dependency_links.txt
prop_test.egg-info/not-zip-safe
prop_test.egg-info/top_level.txt